[
  {
    "title": "adidas",
    "description": "zapatillas blancas",
    "thumbnail": "asdas",
    "code": "3232",
    "stock": "10",
    "id": "8f36c264-0d83-4c37-9746-e5be7ba20982"
  },
  {
    "title": "vans",
    "description": "azules",
    "thumbnail": "dsds",
    "code": "6060",
    "stock": "6060",
    "id": "80581563-3875-4b70-aeb1-83361c79d07b"
  },
  {
    "title": "vans",
    "description": "dsds",
    "thumbnail": "dsds",
    "code": "sdsd",
    "stock": "sfsf",
    "id": "89411657-8e96-461c-9cb6-b8ca0fc409dc"
  }
]